unicorn_hat_sim/__init__.py
unicorn_hat_sim-1.0.0.dist-info/METADATA
unicorn_hat_sim-1.0.0.dist-info/RECORD
unicorn_hat_sim-1.0.0.dist-info/WHEEL
unicorn_hat_sim-1.0.0.dist-info/top_level.txt
