Metadata-Version: 2.1
Name: unicorn-hat-sim
Version: 1.0.0
Summary: Unicorn HAT (HD) simulator - Originally by Jannis Hermanns <jannis@gmail.com>
Home-page: https://github.com/mapitman/unicorn-hat-sim
Author: Mark Pitman
Author-email: mark.pitman@gmail.com
License: MIT
Download-URL: https://github.com/mapitman/unicorn-hat-sim/archive/1.0.0.tar.gz
Keywords: raspberrypi,unicorn,hat,led,simulator
Platform: UNKNOWN
Classifier: Development Status :: 5 - Production/Stable
Classifier: Intended Audience :: Developers
Classifier: License :: OSI Approved :: MIT License
Classifier: Programming Language :: Python :: 2
Classifier: Programming Language :: Python :: 3
Requires-Dist: pygame
